odoo/addons/energy_project/__init__.py
odoo/addons/energy_project/__manifest__.py
odoo/addons/energy_project/backends/__init__.py
odoo/addons/energy_project/backends/arkenova_backend.py
odoo/addons/energy_project/backends/base.py
odoo/addons/energy_project/backends/domain.py
odoo/addons/energy_project/backends/exceptions.py
odoo/addons/energy_project/data/energy_project.reseller.csv
odoo/addons/energy_project/data/energy_project.supplier.csv
odoo/addons/energy_project/data/service_data.xml
odoo/addons/energy_project/data/uom_data.xml
odoo/addons/energy_project/demo/provider_demo.xml
odoo/addons/energy_project/demo/service_available_demo.xml
odoo/addons/energy_project/demo/service_demo.xml
odoo/addons/energy_project/i18n/ca_ES.po
odoo/addons/energy_project/i18n/energy_project.pot
odoo/addons/energy_project/i18n/es.po
odoo/addons/energy_project/i18n/eu_ES.po
odoo/addons/energy_project/models/__init__.py
odoo/addons/energy_project/models/inscription.py
odoo/addons/energy_project/models/project.py
odoo/addons/energy_project/models/project_type.py
odoo/addons/energy_project/models/provider.py
odoo/addons/energy_project/models/reseller.py
odoo/addons/energy_project/models/service.py
odoo/addons/energy_project/models/service_available.py
odoo/addons/energy_project/models/service_contract.py
odoo/addons/energy_project/models/supplier.py
odoo/addons/energy_project/security/ir.model.access.csv
odoo/addons/energy_project/security/ir_rule_data.xml
odoo/addons/energy_project/security/res_groups.xml
odoo/addons/energy_project/services/__init__.py
odoo/addons/energy_project/services/monitoring_service.py
odoo/addons/energy_project/static/description/icon.png
odoo/addons/energy_project/tests/__init__.py
odoo/addons/energy_project/tests/backends_data.example.py
odoo/addons/energy_project/tests/test_backends_arkenova.py
odoo/addons/energy_project/tests/test_monitoring_service.py
odoo/addons/energy_project/tests/test_reseller.py
odoo14_addon_energy_project-14.0.3.5.0.dist-info/METADATA
odoo14_addon_energy_project-14.0.3.5.0.dist-info/WHEEL
odoo14_addon_energy_project-14.0.3.5.0.dist-info/top_level.txt
odoo14_addon_energy_project-14.0.3.5.0.dist-info/RECORD
