Metadata-Version: 2.1
Name: odoo14-addon-energy-project
Version: 14.0.3.5.0
Summary: Base module for energetic projects.
Home-page: https://coopdevs.org
Author: Coopdevs Treball SCCL & Som Energia SCCL
Classifier: Programming Language :: Python
Classifier: Framework :: Odoo
Classifier: Framework :: Odoo :: 14.0
Requires-Python: >=3.6
Requires-Dist: odoo14-addon-account-banking-mandate >=14.0.1.2.0
Requires-Dist: odoo14-addon-cooperator >=14.0.2.1.1
Requires-Dist: odoo <14.1dev,>=14.0a
